django_helmholtz_aai/__init__.py
django_helmholtz_aai/_version.py
django_helmholtz_aai/admin.py
django_helmholtz_aai/app_settings.py
django_helmholtz_aai/apps.py
django_helmholtz_aai/forms.py
django_helmholtz_aai/models.py
django_helmholtz_aai/py.typed
django_helmholtz_aai/signals.py
django_helmholtz_aai/tokens.py
django_helmholtz_aai/urls.py
django_helmholtz_aai/management/__init__.py
django_helmholtz_aai/management/commands/__init__.py
django_helmholtz_aai/management/commands/remove_empty_vos.py
django_helmholtz_aai/migrations/0001_initial.py
django_helmholtz_aai/migrations/0002_auto_20220214_1413.py
django_helmholtz_aai/migrations/0003_auto_20220301_1739.py
django_helmholtz_aai/migrations/0004_auto_20240523_1226.py
django_helmholtz_aai/migrations/__init__.py
django_helmholtz_aai/templatetags/__init__.py
django_helmholtz_aai/templatetags/helmholtz_aai.py
django_helmholtz_aai/views/__init__.py
django_helmholtz_aai/views/auth/__init__.py
django_helmholtz_aai/views/auth/base.py
django_helmholtz_aai/views/auth/create_new.py
django_helmholtz_aai/views/auth/create_new_map_existing_duplicate_helmholtz.py
django_helmholtz_aai/views/auth/create_new_map_existing_no_duplicated_helmholtz.py
django_helmholtz_aai/views/auth/create_new_map_existing_remap_helmholtz.py
django_helmholtz_aai/views/auth/create_new_no_map_duplicate_helmholtz.py
django_helmholtz_aai/views/auth/create_new_no_map_no_duplicated_helmholtz.py
django_helmholtz_aai/views/auth/linking.py
django_helmholtz_aai/views/auth/manual_new_map_existing_no_duplicated_helmholtz.py
django_helmholtz_aai/views/auth/mixins.py
django_helmholtz_aai/views/auth/no_new.py
django_helmholtz_aai/views/auth/no_new_map_existing_no_duplicated_helmholtz.py
django_helmholtz_aai/views/auth/no_new_map_existing_remap_helmholtz.py
django_helmholtz_aai/views/auth/no_new_no_map_duplicate_helmholtz.py
testproject/__init__.py
testproject/database.py
testproject/settings.py
testproject/urls.py
testproject/views.py
testproject/wsgi.py
django_helmholtz_aai-0.2.0.dist-info/CC-BY-4.0.txt
django_helmholtz_aai-0.2.0.dist-info/CC0-1.0.txt
django_helmholtz_aai-0.2.0.dist-info/EUPL-1.2.txt
django_helmholtz_aai-0.2.0.dist-info/METADATA
django_helmholtz_aai-0.2.0.dist-info/WHEEL
django_helmholtz_aai-0.2.0.dist-info/top_level.txt
django_helmholtz_aai-0.2.0.dist-info/RECORD
