Metadata-Version: 2.1
Name: django-helmholtz-aai
Version: 0.2.0
Summary: A generic Django app to login via Helmholtz AAI
Author-email: "Philipp S. Sommer" <philipp.sommer@hereon.de>, Housam Dibeh <hcdc_support@hereon.de>, Hatef Takyar <hcdc_support@hereon.de>
Maintainer-email: "Philipp S. Sommer" <philipp.sommer@hereon.de>
License: EUPL-1.2
Project-URL: Homepage, https://codebase.helmholtz.cloud/hcdc/django/django-helmholtz-aai
Project-URL: Documentation, https://django-helmholtz-aai.readthedocs.io/en/latest/
Project-URL: Source, https://codebase.helmholtz.cloud/hcdc/django/django-helmholtz-aai
Project-URL: Tracker, https://codebase.helmholtz.cloud/hcdc/django/django-helmholtz-aai/issues/
Keywords: Helmholtz AAI,authlib,oauth,hifis,login,hgf
Classifier: Intended Audience :: Developers
Classifier: License :: OSI Approved :: European Union Public Licence 1.2 (EUPL 1.2)
Classifier: Operating System :: OS Independent
Classifier: Programming Language :: Python
Classifier: Programming Language :: Python :: 3
Classifier: Programming Language :: Python :: 3 :: Only
Classifier: Programming Language :: Python :: 3.9
Classifier: Programming Language :: Python :: 3.10
Classifier: Typing :: Typed
Requires-Python: >=3.9
License-File: LICENSES/CC-BY-4.0.txt
License-File: LICENSES/CC0-1.0.txt
License-File: LICENSES/EUPL-1.2.txt
Requires-Dist: Django >=3.1
Requires-Dist: authlib
Requires-Dist: requests
Provides-Extra: dev
Requires-Dist: django-helmholtz-aai[testsite] ; extra == 'dev'
Requires-Dist: django-helmholtz-aai[docs] ; extra == 'dev'
Requires-Dist: PyYAML ; extra == 'dev'
Requires-Dist: types-PyYAML ; extra == 'dev'
Provides-Extra: docs
Requires-Dist: autodocsumm ; extra == 'docs'
Requires-Dist: sphinx-rtd-theme ; extra == 'docs'
Requires-Dist: hereon-netcdf-sphinxext ; extra == 'docs'
Requires-Dist: sphinx-design ; extra == 'docs'
Requires-Dist: django-environ ; extra == 'docs'
Provides-Extra: testsite
Requires-Dist: tox ; extra == 'testsite'
Requires-Dist: isort ==5.12.0 ; extra == 'testsite'
Requires-Dist: black ==23.1.0 ; extra == 'testsite'
Requires-Dist: blackdoc ==0.3.8 ; extra == 'testsite'
Requires-Dist: flake8 ==6.0.0 ; extra == 'testsite'
Requires-Dist: pre-commit ; extra == 'testsite'
Requires-Dist: mypy ==1.4.1 ; extra == 'testsite'
Requires-Dist: pytest-cov ; extra == 'testsite'
Requires-Dist: reuse ; extra == 'testsite'
Requires-Dist: cffconvert ; extra == 'testsite'
Requires-Dist: django-environ ; extra == 'testsite'
Requires-Dist: django-stubs ==4.2.3 ; extra == 'testsite'
Requires-Dist: pytest-django ; extra == 'testsite'
